{
  "problems": [
    {"id": 4, "title": "Median of Two Sorted Arrays", "slug": "median-of-two-sorted-arrays"},
    {"id": 10, "title": "Regular Expression Matching", "slug": "regular-expression-matching"},
    {"id": 23, "title": "Merge k Sorted Lists", "slug": "merge-k-sorted-lists"},
    {"id": 25, "title": "Reverse Nodes in k-Group", "slug": "reverse-nodes-in-k-group"},
    {"id": 30, "title": "Substring with Concatenation of All Words", "slug": "substring-with-concatenation-of-all-words"}
  ]
}
